unformat-0.1.3.dist-info/METADATA
unformat-0.1.3.dist-info/WHEEL
unformat-0.1.3.dist-info/license_files/LICENSE
unformat/core.py
unformat/_unformat_rust.pyi
unformat/__init__.py
unformat/_unformat_rust.cp310-win_amd64.pyd
unformat-0.1.3.dist-info/RECORD
