Metadata-Version: 2.1
Name: unformat
Version: 0.1.3
Classifier: Programming Language :: Python
Classifier: Programming Language :: Python :: 3
Classifier: Programming Language :: Python :: 3 :: Only
Classifier: Programming Language :: Python :: 3.8
Classifier: Programming Language :: Python :: 3.9
Classifier: Programming Language :: Python :: 3.10
Classifier: Programming Language :: Python :: 3.11
License-File: LICENSE
Summary: Python string unformatter.
Home-Page: https://github.com/hanjinliu/unformat
Requires-Python: >=3.8
Project-URL: Source Code, https://github.com/hanjinliu/unformat.git
